{
  "/_app": "pages/_app.js",
  "/_error": "pages/_error.js",
  "/Auth": "pages/Auth.js",
  "/CreatePost": "pages/CreatePost.js",
  "/Feed": "pages/Feed.js",
  "/HowItWorks": "pages/HowItWorks.js",
  "/FindTeacher": "pages/FindTeacher.js",
  "/MyPosts": "pages/MyPosts.js",
  "/Index": "pages/Index.js",
  "/NotFound": "pages/NotFound.js",
  "/RootRedirect": "pages/RootRedirect.js",
  "/SignUp": "pages/SignUp.js",
  "/StudentDashboard": "pages/StudentDashboard.js",
  "/TeacherProfile": "pages/TeacherProfile.js",
  "/TeacherOnboarding": "pages/TeacherOnboarding.js",
  "/TeacherDashboard": "pages/TeacherDashboard.js",
  "/_document": "pages/_document.js"
}